setup.py
Products/__init__.py
Products.AttachmentField.egg-info/PKG-INFO
Products.AttachmentField.egg-info/SOURCES.txt
Products.AttachmentField.egg-info/dependency_links.txt
Products.AttachmentField.egg-info/entry_points.txt
Products.AttachmentField.egg-info/namespace_packages.txt
Products.AttachmentField.egg-info/not-zip-safe
Products.AttachmentField.egg-info/requires.txt
Products.AttachmentField.egg-info/top_level.txt
Products/AttachmentField/ABOUT
Products/AttachmentField/AttachmentField.py
Products/AttachmentField/AttachmentFieldTool.py
Products/AttachmentField/AttachmentHandler.py
Products/AttachmentField/AttachmentService.py
Products/AttachmentField/AttachmentWidget.py
Products/AttachmentField/AudioAttachment.py
Products/AttachmentField/AutocadAttachment.py
Products/AttachmentField/CHANGES
Products/AttachmentField/CompressedAttachment.py
Products/AttachmentField/DummyAttachment.py
Products/AttachmentField/FlashAttachment.py
Products/AttachmentField/FlexStorage.py
Products/AttachmentField/HTMLAttachment.py
Products/AttachmentField/ImageAttachment.py
Products/AttachmentField/LICENSE
Products/AttachmentField/MSAccessAttachment.py
Products/AttachmentField/MSExcelAttachment.py
Products/AttachmentField/MSPowerpointAttachment.py
Products/AttachmentField/MSProjectAttachment.py
Products/AttachmentField/MSWordAttachment.py
Products/AttachmentField/OO2Attachment.py
Products/AttachmentField/OOAttachment.py
Products/AttachmentField/OpenXmlAttachment.py
Products/AttachmentField/PDFAttachment.py
Products/AttachmentField/PSAttachment.py
Products/AttachmentField/PhotoshopAttachment.py
Products/AttachmentField/PortalTransformsAttachment.py
Products/AttachmentField/README.txt
Products/AttachmentField/RTFAttachment.py
Products/AttachmentField/TESTED_WITH
Products/AttachmentField/TarGzAttachment.py
Products/AttachmentField/TextAttachment.py
Products/AttachmentField/TypelessAttachmentField.py
Products/AttachmentField/VideoAttachment.py
Products/AttachmentField/VisioAttachment.py
Products/AttachmentField/ZipAttachment.py
Products/AttachmentField/__init__.py
Products/AttachmentField/cvs2cl.pl
Products/AttachmentField/global_symbols.py
Products/AttachmentField/ooconverter.py
Products/AttachmentField/product.txt
Products/AttachmentField/striphtml.py
Products/AttachmentField/tool.gif
Products/AttachmentField/version.txt
Products/AttachmentField/Extensions/Install.py
