Metadata-Version: 1.1
Name: Products.AttachmentField
Version: 1.4.6
Summary: AttachmentField/Widget for Plone
Home-page: http://github.com/collective/Products.AttachmentField
Author: Alex Clark
Author-email: aclark@aclark.net
License: GPL
Keywords: Plone
Platform: UNKNOWN
Classifier: Programming Language :: Python
Classifier: Framework :: Plone
Classifier: Topic :: Software Development :: Libraries :: Python Modules
